colorlog/__init__.py
colorlog/colorlog.py
colorlog_jawide-0.0.1.dist-info/LICENSE
colorlog_jawide-0.0.1.dist-info/METADATA
colorlog_jawide-0.0.1.dist-info/WHEEL
colorlog_jawide-0.0.1.dist-info/top_level.txt
colorlog_jawide-0.0.1.dist-info/RECORD
