Metadata-Version: 2.1
Name: colorlog-jawide
Version: 0.0.1
Summary: Enable the default logging to output with color
Home-page: https://github.com/jawide/colorlog
Author: jawide
Author-email: jawide@qq.com
License: UNKNOWN
Project-URL: Bug Tracker, https://github.com/jawide/colorlog/issues
Platform: UNKNOWN
Classifier: Programming Language :: Python :: 3
Classifier: License :: OSI Approved :: MIT License
Classifier: Operating System :: OS Independent
Requires-Python: >=3.6
